simplecalcpypip/__init__.py
simplecalcpypip/simplecalcpypip.py
simplecalcpypip/simpleplot.py
simplecalcpypip-0.1.1.dist-info/LICENSE
simplecalcpypip-0.1.1.dist-info/METADATA
simplecalcpypip-0.1.1.dist-info/WHEEL
simplecalcpypip-0.1.1.dist-info/RECORD
