Metadata-Version: 2.1
Name: simplecalcpypip
Version: 0.1.1
Summary: Hands-on of packages documentation using pip
License: MIT
Author: TestPipDocs
Requires-Python: >=3.9
Classifier: License :: OSI Approved :: MIT License
Classifier: Programming Language :: Python :: 3
Classifier: Programming Language :: Python :: 3.9
Classifier: Programming Language :: Python :: 3.10
Classifier: Programming Language :: Python :: 3.11
Classifier: Programming Language :: Python :: 3.12
Requires-Dist: matplotlib (>=3.8.2)
